jupyterlite_terminal/__init__.py
jupyterlite_terminal/_version.py
jupyterlite_terminal/add_on.py
jupyterlite_terminal-1.2.0.data/data/share/jupyter/labextensions/jupyterlite-terminal/package.json
jupyterlite_terminal-1.2.0.data/data/share/jupyter/labextensions/jupyterlite-terminal/static/17.5e9d2991bef84a7c93eb.js
jupyterlite_terminal-1.2.0.data/data/share/jupyter/labextensions/jupyterlite-terminal/static/17.5e9d2991bef84a7c93eb.js.LICENSE.txt
jupyterlite_terminal-1.2.0.data/data/share/jupyter/labextensions/jupyterlite-terminal/static/173.e7965506d42fe50e7a40.js
jupyterlite_terminal-1.2.0.data/data/share/jupyter/labextensions/jupyterlite-terminal/static/385.754b452e63b1f1199661.js
jupyterlite_terminal-1.2.0.data/data/share/jupyter/labextensions/jupyterlite-terminal/static/398.6059ed647fd71c7b9aa6.js
jupyterlite_terminal-1.2.0.data/data/share/jupyter/labextensions/jupyterlite-terminal/static/398.6059ed647fd71c7b9aa6.js.LICENSE.txt
jupyterlite_terminal-1.2.0.data/data/share/jupyter/labextensions/jupyterlite-terminal/static/63.daf0f4b5311c8376417b.js
jupyterlite_terminal-1.2.0.data/data/share/jupyter/labextensions/jupyterlite-terminal/static/644.281178105052acadf409.js
jupyterlite_terminal-1.2.0.data/data/share/jupyter/labextensions/jupyterlite-terminal/static/671.d26457da6cb7180e13ce.js
jupyterlite_terminal-1.2.0.data/data/share/jupyter/labextensions/jupyterlite-terminal/static/671.d26457da6cb7180e13ce.js.LICENSE.txt
jupyterlite_terminal-1.2.0.data/data/share/jupyter/labextensions/jupyterlite-terminal/static/728.40a47300f2daff234096.js
jupyterlite_terminal-1.2.0.data/data/share/jupyter/labextensions/jupyterlite-terminal/static/886.611086790b8182c9b079.js
jupyterlite_terminal-1.2.0.data/data/share/jupyter/labextensions/jupyterlite-terminal/static/886.611086790b8182c9b079.js.LICENSE.txt
jupyterlite_terminal-1.2.0.data/data/share/jupyter/labextensions/jupyterlite-terminal/static/974.0009e7c7ceb44725b1de.js
jupyterlite_terminal-1.2.0.dist-info/METADATA
jupyterlite_terminal-1.2.0.dist-info/WHEEL
jupyterlite_terminal-1.2.0.dist-info/entry_points.txt
jupyterlite_terminal-1.2.0.dist-info/licenses/LICENSE
jupyterlite_terminal-1.2.0.dist-info/RECORD
