Metadata-Version: 2.4
Name: jupyterlite_terminal
Version: 1.2.0
Dynamic: Keywords
Summary: A terminal for JupyterLite
Project-URL: Homepage, https://github.com/jupyterlite/terminal
Project-URL: Bug Tracker, https://github.com/jupyterlite/terminal/issues
Project-URL: Repository, https://github.com/jupyterlite/terminal.git
Author: JupyterLite Contributors
License: BSD 3-Clause License
License-File: LICENSE
Classifier: Framework :: Jupyter
Classifier: Framework :: Jupyter :: JupyterLab
Classifier: Framework :: Jupyter :: JupyterLab :: 4
Classifier: Framework :: Jupyter :: JupyterLab :: Extensions
Classifier: Framework :: Jupyter :: JupyterLab :: Extensions :: Prebuilt
Classifier: License :: OSI Approved :: BSD License
Classifier: Programming Language :: Python
Classifier: Programming Language :: Python :: 3
Classifier: Programming Language :: Python :: 3.10
Classifier: Programming Language :: Python :: 3.11
Classifier: Programming Language :: Python :: 3.12
Classifier: Programming Language :: Python :: 3.13
Classifier: Programming Language :: Python :: 3.14
Requires-Python: >=3.10
Requires-Dist: jupyterlite-core<0.8.0,>=0.7.0
